RandoMorph/__init__.py
RandoMorph/test.py
RandoMorph-0.0.8.dist-info/METADATA
RandoMorph-0.0.8.dist-info/WHEEL
RandoMorph-0.0.8.dist-info/top_level.txt
RandoMorph-0.0.8.dist-info/RECORD
