Metadata-Version: 2.1
Name: RandoMorph
Version: 0.0.8
Summary: A simple Python library for generating random data of various types, including strings, names, addresses, numbers, and more.
Home-page: https://github.com/soyll/RandoMorph
Author: soyll
Author-email: soyll@vk.com
Project-URL: GitHub, https://github.com/soyll
Keywords: test python generate random randomorph
Classifier: Programming Language :: Python :: 3.11
Classifier: License :: OSI Approved :: MIT License
Classifier: Operating System :: OS Independent
Requires-Python: >=3.6
Requires-Dist: pandas (~=2.1.1)
Requires-Dist: dataframe-image (~=0.2.2)
Requires-Dist: openpyxl (~=3.1.2)
